hive_intelligence/__init__.py
hive_intelligence/client.py
hive_intelligence/errors.py
hive_intelligence/types.py
hive_intelligence-0.1.0.dist-info/METADATA
hive_intelligence-0.1.0.dist-info/WHEEL
hive_intelligence-0.1.0.dist-info/RECORD
