Metadata-Version: 2.3
Name: hive-intelligence
Version: 0.1.0
Summary: Hive intelligence SDK
Requires-Python: >=3.9
Classifier: Programming Language :: Python :: 3
Classifier: Programming Language :: Python :: 3.9
Classifier: Programming Language :: Python :: 3.10
Classifier: Programming Language :: Python :: 3.11
Classifier: Programming Language :: Python :: 3.12
Classifier: Programming Language :: Python :: 3.13
Requires-Dist: pydantic (>=2.11.3,<3.0.0)
Requires-Dist: requests (>=2.32.3,<3.0.0)
